vmem/__init__.py
vmem/osx.py
vmem/posix.py
vmem/utils.py
vmem/windows.py
vmem-1.0.1.dist-info/LICENSE
vmem-1.0.1.dist-info/METADATA
vmem-1.0.1.dist-info/WHEEL
vmem-1.0.1.dist-info/top_level.txt
vmem-1.0.1.dist-info/RECORD
