Metadata-Version: 2.1
Name: vmem
Version: 1.0.1
Summary: Cross-platform virtual memory information
Home-page: https://github.com/pierotofy/vmem
Author: Piero Toffanin
Author-email: pt@uav4geo.com
License: UNKNOWN
Platform: UNKNOWN
Classifier: Programming Language :: Python :: 3
Classifier: License :: OSI Approved :: GNU General Public License v3 or later (GPLv3+)
Classifier: Operating System :: OS Independent
